zimran/fastapi/__init__.py
zimran/fastapi/dependencies.py
zimran_fastapi-2.1.0.dist-info/METADATA
zimran_fastapi-2.1.0.dist-info/WHEEL
zimran_fastapi-2.1.0.dist-info/top_level.txt
zimran_fastapi-2.1.0.dist-info/RECORD
