Metadata-Version: 2.4
Name: zimran-fastapi
Version: 2.1.0
Summary: Preconfigured FastAPI application
Requires-Python: >=3.11
Requires-Dist: fastapi[standard]
Requires-Dist: zimran-config==1.1.*
Requires-Dist: loguru==0.7.3
Requires-Dist: user-agents==2.2.0
Dynamic: description
Dynamic: description-content-type
Dynamic: requires-dist
Dynamic: requires-python
Dynamic: summary
